{
  "crescent_moon": {
    "id": "crescent_moon",
    "name": "Crescent Moon",
    "gifts": [
      {
        "id": "two_world_eyes",
        "level": 1,
        "name": "Two-World Eyes",
        "cost": "None",
        "dice": "Wits + Occult + Wisdom",
        "action": "Instant",
        "description": "The Ithaeur can peer across the Gauntlet without sacrificing her perception of either world, seeing both simultaneously for the duration of the scene."
      },
      {
        "id": "read_spirit",
        "level": 2,
        "name": "Read Spirit",
        "cost": "1 Essence",
        "dice": "Intelligence + Occult + Cunning",
        "action": "Instant",
        "description": "The werewolf hears an internal voice that reveals a spirit's name, type, Rank, and one pertinent fact per success rolled."
      },
      {
        "id": "gauntlet_cloak",
        "level": 3,
        "name": "Gauntlet Cloak",
        "cost": "1 Essence",
        "dice": "Dexterity + Occult + Purity",
        "action": "Instant",
        "description": "The Ithaeur wraps the Gauntlet around herself, gaining a –2 concealment modifier against ranged attacks and imposing penalties on attempts to spot or recognize her."
      },
      {
        "id": "between_the_weave",
        "level": 4,
        "name": "Between the Weave",
        "cost": "1 Essence",
        "dice": "No roll required",
        "action": "Reflexive",
        "description": "The Ithaeur can cross the Gauntlet as a reflexive action and still take a normal action in the same turn, leaping between worlds to attack or escape with ease."
      },
      {
        "id": "crash_the_gates",
        "level": 5,
        "name": "Crash the Gates",
        "cost": "1 Essence + 1 per packmate",
        "dice": "No roll required",
        "action": "Instant",
        "description": "The Ithaeur extends Between the Weave to her packmates, allowing the entire pack to cross the Gauntlet simultaneously in a single action."
      }
    ]
  },
  "death": {
    "id": "death",
    "name": "Death",
    "gifts": [
      {
        "id": "death_sight",
        "level": 1,
        "name": "Death Sight",
        "cost": "None",
        "dice": "No roll required",
        "action": "Instant",
        "description": "The werewolf's sight attunes to the dead: he perceives ghosts and phantom bloodstains marking where creatures died within the last lunar month."
      },
      {
        "id": "ghost_knife",
        "level": 2,
        "name": "Ghost Knife",
        "cost": "1 Essence",
        "dice": "No roll required",
        "action": "Instant",
        "description": "The werewolf imbues a weapon with Essence, making it capable of striking immaterial ghosts as readily as physical targets, and adding a bonus die to attack rolls against spirits."
      },
      {
        "id": "corpse_witness",
        "level": 3,
        "name": "Corpse Witness",
        "cost": "1 Essence",
        "dice": "Manipulation + Occult + Purity",
        "action": "Instant",
        "description": "The werewolf breathes into a corpse's mouth; the corpse reports everything it perceived since its death, useful for uncovering what transpired at a crime scene."
      },
      {
        "id": "word_of_quiet",
        "level": 4,
        "name": "Word of Quiet",
        "cost": "1 Willpower",
        "dice": "Presence + Occult + Honor – subject's Stamina",
        "action": "Instant",
        "description": "The werewolf speaks a word in the First Tongue that inflicts bashing damage on living creatures in range and lethal damage on undead within hearing."
      },
      {
        "id": "vengeance_of_the_slain",
        "level": 5,
        "name": "Vengeance of the Slain",
        "cost": "1 Essence",
        "dice": "Stamina + Occult + Wisdom",
        "action": "Instant",
        "description": "The werewolf briefly returns a recently deceased Uratha to a semblance of life for roughly one hour per success, allowing her to act and use her supernatural powers."
      }
    ]
  },
  "dominance": {
    "id": "dominance",
    "name": "Dominance",
    "gifts": [
      {
        "id": "warning_growl",
        "level": 1,
        "name": "Warning Growl",
        "cost": "1 Willpower",
        "dice": "Presence + Intimidation + Glory vs. Composure + Primal Urge",
        "action": "Contested; resistance is reflexive",
        "description": "The werewolf's supernatural growl strikes sudden doubt into a target, giving the Gift user a +2 Defense bonus against that target's close-combat attacks for the duration of the scene."
      },
      {
        "id": "lunas_dictum",
        "level": 2,
        "name": "Luna's Dictum",
        "cost": "1 Willpower",
        "dice": "Presence + Intimidation + Glory vs. Composure + Primal Urge",
        "action": "Contested; resistance is reflexive",
        "description": "The werewolf voices a brief command that compels a single target to obey for up to five minutes per success rolled."
      },
      {
        "id": "voice_of_command",
        "level": 3,
        "name": "Voice of Command",
        "cost": "1 Essence",
        "dice": "Manipulation + Intimidation + Honor vs. Resolve + Primal Urge",
        "action": "Contested; resistance is reflexive",
        "description": "The werewolf issues a decree affecting up to three targets, each of whom must obey a specific command given, suffering –1 to the roll per target after the first."
      },
      {
        "id": "break_the_defiant",
        "level": 4,
        "name": "Break the Defiant",
        "cost": "1 Essence",
        "dice": "Presence + Intimidation + Purity – subject's Resolve",
        "action": "Instant",
        "description": "The werewolf projects crushing authority, causing the target to immediately lose Willpower equal to the number of successes rolled."
      },
      {
        "id": "tug_the_souls_strings",
        "level": 5,
        "name": "Tug the Soul's Strings",
        "cost": "1 Essence",
        "dice": "Manipulation + Persuasion + Cunning vs. Resolve + Primal Urge",
        "action": "Contested; resistance is reflexive",
        "description": "The werewolf can force another person to perform deeds against her will, including deeds that defy her identity or cause harm to others."
      }
    ]
  },
  "elemental": {
    "id": "elemental",
    "name": "Elemental",
    "gifts": [
      {
        "id": "call_water",
        "level": 1,
        "name": "Call Water",
        "cost": "None",
        "dice": "Stamina + Survival + Purity",
        "action": "Instant",
        "description": "The werewolf summons water from thin air, creating one cup per success — enough to stave off death from dehydration. Cannot be invoked more than once an hour."
      },
      {
        "id": "manipulate_earth",
        "level": 2,
        "name": "Manipulate Earth",
        "cost": "1 Essence",
        "dice": "Dexterity + Crafts + Cunning",
        "action": "Instant",
        "description": "The werewolf shapes earth as if it were clay, sculpting a surface area of roughly 100 square feet or 40 cubic feet for cover or escape. Changes are permanent."
      },
      {
        "id": "command_fire",
        "level": 3,
        "name": "Command Fire",
        "cost": "1 Essence",
        "dice": "Strength + Survival + Glory",
        "action": "Instant",
        "description": "The werewolf commands existing flames within line of sight, directing them at a target within 20 yards for one die of fire damage per success."
      },
      {
        "id": "invoke_the_winds_wrath",
        "level": 4,
        "name": "Invoke the Wind's Wrath",
        "cost": "2 Essence",
        "dice": "Strength + Empathy + Honor",
        "action": "Instant",
        "description": "The werewolf calls a whirlwind of 10-foot radius that moves at his Speed, lifting those 150 lbs. or less and inflicting one die of lethal damage per success."
      },
      {
        "id": "lament_of_the_river",
        "level": 5,
        "name": "Lament of the River",
        "cost": "3 Essence",
        "dice": "Stamina + Intimidation + Wisdom",
        "action": "Extended (50 successes; each roll = one minute of concentration)",
        "description": "The werewolf calls rivers and streams to burst their banks, causing devastating floods across one square mile when 50 successes are accumulated."
      }
    ]
  },
  "evasion": {
    "id": "evasion",
    "name": "Evasion",
    "gifts": [
      {
        "id": "loose_tongue",
        "level": 1,
        "name": "Loose Tongue",
        "cost": "None",
        "dice": "Manipulation + Socialize + Wisdom vs. Composure + Primal Urge",
        "action": "Contested; resistance is reflexive",
        "description": "The werewolf's presence makes targets oddly chatty and susceptible to 'friendly conversation,' lowering their guard and making them less able to keep secrets."
      },
      {
        "id": "sand_in_the_eyes",
        "level": 2,
        "name": "Sand in the Eyes",
        "cost": "None",
        "dice": "Manipulation + Subterfuge + Honor vs. Composure + Primal Urge",
        "action": "Contested; resistance is reflexive",
        "description": "The werewolf becomes imminently forgettable; subjects suffer a –5 penalty to Intelligence + Composure rolls to remember details about her for the rest of the scene."
      },
      {
        "id": "playing_possum",
        "level": 3,
        "name": "Playing Possum",
        "cost": "1 Willpower",
        "dice": "Wits + Subterfuge + Cunning",
        "action": "Reflexive",
        "description": "The werewolf appears freshly dead — no pulse, breathing, or warmth — for up to one day, and can revive as an instant action at will."
      },
      {
        "id": "double_back",
        "level": 4,
        "name": "Double Back",
        "cost": "1 Willpower",
        "dice": "Intelligence + Investigation + Glory",
        "action": "Reflexive",
        "description": "The werewolf becomes immediately aware of all physical deception in her environment — hidden trails, disguises, concealed evidence — and cannot be fooled by such for the rest of the scene."
      },
      {
        "id": "fog_of_war",
        "level": 5,
        "name": "Fog of War",
        "cost": "1 Essence",
        "dice": "Manipulation + Expression + Honor vs. Resolve + Primal Urge",
        "action": "Contested; resistance is reflexive",
        "description": "The werewolf's howl sows confusion; all targets within extreme hearing range suffer a –3 penalty to all actions for as long as the werewolf concentrates."
      }
    ]
  },
  "father_wolf": {
    "id": "father_wolf",
    "name": "Father Wolf's",
    "gifts": [
      {
        "id": "wolf_bloods_lure",
        "level": 1,
        "name": "Wolf-Blood's Lure",
        "cost": "None",
        "dice": "No roll required",
        "action": "Reflexive",
        "description": "The werewolf projects his wolf soul more strongly, gaining a bonus die on all Social rolls involving wolves or canids and earning the trust of wolf packs with ease. Lasts from moonrise to moonrise."
      },
      {
        "id": "father_wolfs_speed",
        "level": 2,
        "name": "Father Wolf's Speed",
        "cost": "1 Essence",
        "dice": "No roll required",
        "action": "Reflexive",
        "description": "The werewolf's Speed is doubled (after modifiers) and opponents suffer –2 to Firearms dice pools against him; the effects last for a scene."
      },
      {
        "id": "primal_howl",
        "level": 3,
        "name": "Primal Howl",
        "cost": "1 Essence",
        "dice": "Presence + Expression + Purity vs. Composure",
        "action": "Contested; resistance is reflexive",
        "description": "The werewolf's howl overwhelms those who hear it with primal fear as if affected by Lunacy, affecting all targets within 10 yards per dot of Primal Urge."
      },
      {
        "id": "savage_rending",
        "level": 4,
        "name": "Savage Rending",
        "cost": "1 Essence",
        "dice": "No roll required",
        "action": "Reflexive",
        "description": "The werewolf's claw and bite attacks inflict aggravated damage for the duration of the scene. Using this Gift against other werewolves is considered a sin against Harmony."
      },
      {
        "id": "spirit_pack",
        "level": 5,
        "name": "Spirit Pack",
        "cost": "1 Essence",
        "dice": "Manipulation + Animal Ken + Glory",
        "action": "Instant",
        "description": "The werewolf howls a battle cry summoning one ghostly Wolf-Brother spirit per success to fight alongside him until there are no more enemies or the Gift user is slain."
      }
    ]
  },
  "full_moon": {
    "id": "full_moon",
    "name": "Full Moon",
    "gifts": [
      {
        "id": "clarity",
        "level": 1,
        "name": "Clarity",
        "cost": "1 Essence",
        "dice": "No roll required",
        "action": "Reflexive",
        "description": "The werewolf increases his Initiative modifier by five for the remainder of the fight, greatly improving his odds of striking first in battle."
      },
      {
        "id": "attunement",
        "level": 2,
        "name": "Attunement",
        "cost": "1 Willpower",
        "dice": "Wits + Brawl + Wisdom – opponent's Resolve",
        "action": "Reflexive",
        "description": "After one full turn observing a foe, the werewolf can ignore a portion of that opponent's Defense equal to half his Primal Urge (rounded up) for the rest of the scene."
      },
      {
        "id": "death_grip",
        "level": 3,
        "name": "Death Grip",
        "cost": "1 Essence per bite attack",
        "dice": "Strength + Brawl + Glory",
        "action": "Reflexive",
        "description": "The werewolf's jaws lock with supernatural force: bite damage is doubled and the victim suffers a penalty to breaking free or performing overpower maneuvers."
      },
      {
        "id": "rage_armor",
        "level": 4,
        "name": "Rage Armor",
        "cost": "1 Essence",
        "dice": "Stamina + Survival + Honor",
        "action": "Instant",
        "description": "The werewolf tempers his flesh with Rage, gaining one point of Armor per two successes rolled; the armor lasts for a number of turns equal to his Primal Urge dots."
      },
      {
        "id": "lunas_fury",
        "level": 5,
        "name": "Luna's Fury",
        "cost": "1 Essence per turn",
        "dice": "Dexterity + Empathy + Cunning",
        "action": "Instant",
        "description": "The werewolf becomes a vessel for Luna's wrath: his Defense doubles against incoming attacks, he gains two extra dice on close-combat attacks, and all attacks can be staged normally."
      }
    ]
  },
  "gibbous_moon": {
    "id": "gibbous_moon",
    "name": "Gibbous Moon",
    "gifts": [
      {
        "id": "pack_awareness",
        "level": 1,
        "name": "Pack Awareness",
        "cost": "None",
        "dice": "Wits + Empathy + Wisdom",
        "action": "Reflexive",
        "description": "The Cahalith immediately senses where her packmates are, what form each is in, their general activity, and their state of being — including wound penalties and unconsciousness. Lasts one scene."
      },
      {
        "id": "resist_pain",
        "level": 2,
        "name": "Resist Pain",
        "cost": "1 Willpower",
        "dice": "Stamina + Survival + Honor",
        "action": "Instant",
        "description": "The Cahalith ignores wound penalties, acting with a full dice pool until her last Health points are healed or she falls unconscious; she is also not threatened by Death Rage from her last three Health boxes. Lasts the remainder of the scene."
      },
      {
        "id": "rallying_cry",
        "level": 3,
        "name": "Rallying Cry",
        "cost": "1 Willpower",
        "dice": "Manipulation + Expression + Glory",
        "action": "Instant",
        "description": "The Cahalith channels the voices of the Cahalunim through her, inspiring packmates with tales of glory; each packmate regains one spent Willpower point on a success."
      },
      {
        "id": "unspoken_communication",
        "level": 4,
        "name": "Unspoken Communication",
        "cost": "1 Essence",
        "dice": "Intelligence + Socialize + Purity",
        "action": "Instant",
        "description": "Packmates within line of sight are joined in instantaneous mental communication for the scene, able to speak mind to mind and gaining a +3 bonus to Initiative."
      },
      {
        "id": "call_of_glory",
        "level": 5,
        "name": "Call of Glory",
        "cost": "1 Willpower",
        "dice": "Presence + Expression + Glory",
        "action": "Instant",
        "description": "The Cahalith sings a battle hymn invoking the Lunes of the gibbous moon; each success heals one point of damage — bashing, lethal, or aggravated — for each of her packmates."
      }
    ]
  },
  "half_moon": {
    "id": "half_moon",
    "name": "Half Moon",
    "gifts": [
      {
        "id": "scent_beneath_the_surface",
        "level": 1,
        "name": "Scent Beneath the Surface",
        "cost": "1 Willpower",
        "dice": "Wits + Empathy + Purity versus deceiver's Composure + Primal Urge",
        "action": "Contested; resistance is reflexive",
        "description": "After paying close attention to someone for one turn, the Elodoth gains insight into whether the subject is lying outright, misleading by omission, being evasive, or concealing her emotional state."
      },
      {
        "id": "snarl_of_command",
        "level": 2,
        "name": "Snarl of Command",
        "cost": "1 Willpower",
        "dice": "Presence + Intimidation + Cunning versus subject's Composure + Primal Urge",
        "action": "Contested; resistance is reflexive",
        "description": "With a snarl and harsh words, the Elodoth compels a subject to reveal the simple truth behind a topic of contention, forcing one true answer from a liar's mouth."
      },
      {
        "id": "aura_of_truce",
        "level": 3,
        "name": "Aura of Truce",
        "cost": "1 Essence",
        "dice": "Manipulation + Persuasion + Honor",
        "action": "Instant",
        "description": "A subtle half-moon halo appears behind the Elodoth, calming the area for the scene; committing any violent act — attack, damaging property, or using a Gift against an unwilling subject — requires spending a Willpower point reflexively."
      },
      {
        "id": "fuel_rage",
        "level": 4,
        "name": "Fuel Rage",
        "cost": "1 Essence",
        "dice": "Stamina + Occult + Purity",
        "action": "Instant",
        "description": "Used before or upon assuming Gauru form, this Gift increases the number of turns the Elodoth can remain in Gauru by a number of turns equal to the successes rolled."
      },
      {
        "id": "bind_or_sunder",
        "level": 5,
        "name": "Bind or Sunder",
        "cost": "1 Essence",
        "dice": "Stamina + Occult + Purity (to extend); Manipulation + Occult + Cunning – resisting subject's Resolve (to reduce)",
        "action": "Instant",
        "description": "The Elodoth can increase or decrease the number of turns a werewolf of his choice remains in Gauru form, with each success adding or subtracting one turn."
      }
    ]
  },
  "insight": {
    "id": "insight",
    "name": "Insight",
    "gifts": [
      {
        "id": "sense_malice",
        "level": 1,
        "name": "Sense Malice",
        "cost": "None",
        "dice": "Intelligence + Empathy + Wisdom versus subject's Composure + Primal Urge",
        "action": "Contested; resistance is reflexive",
        "description": "The werewolf can smell malice, hatred, anger, or envy lurking in other people's hearts, detecting powerful negative emotions in those close enough to scent."
      },
      {
        "id": "scent_of_taint",
        "level": 2,
        "name": "Scent of Taint",
        "cost": "None",
        "dice": "Wits + Occult + Purity",
        "action": "Instant",
        "description": "The werewolf can detect the presence of supernatural beings in his vicinity by sensing powers that defy the natural order of the physical and spirit worlds."
      },
      {
        "id": "echo_dream",
        "level": 3,
        "name": "Echo Dream",
        "cost": "1 Essence",
        "dice": "Wits + Investigation + Honor",
        "action": "Instant",
        "description": "By holding an object or resting her hand against a surface, the Forsaken senses spirit echoes of the object or area's recent past, couched in the symbolic language of the spirit world."
      },
      {
        "id": "soul_read",
        "level": 4,
        "name": "Soul Read",
        "cost": "1 Essence",
        "dice": "Intelligence + Empathy + Purity versus subject's Resolve + Primal Urge",
        "action": "Contested; resistance is reflexive",
        "description": "The character looks directly into the heart of a subject, reading the worst fears, secrets, and sins hidden there — gaining knowledge of one secret, fear, or weakness per success."
      },
      {
        "id": "omen_gazing",
        "level": 5,
        "name": "Omen Gazing",
        "cost": "1 Essence",
        "dice": "Resolve + Occult + Glory",
        "action": "Extended (15 successes required; each roll represents one minute spent in a trance)",
        "description": "The character enters a meditative trance and catches glimpses of the future, such as warnings of an impending attack or a potential event within the next 24 hours to one week."
      }
    ]
  },
  "inspiration": {
    "id": "inspiration",
    "name": "Inspiration",
    "gifts": [
      {
        "id": "the_right_words",
        "level": 1,
        "name": "The Right Words",
        "cost": "None",
        "dice": "No roll required",
        "action": "Reflexive",
        "description": "The character gains +2 to all Social rolls made to encourage or mollify; Social rolls to bully or threaten are not affected. The effects last for a scene."
      },
      {
        "id": "camaraderie",
        "level": 2,
        "name": "Camaraderie",
        "cost": "None",
        "dice": "Manipulation + Persuasion + Wisdom",
        "action": "Reflexive",
        "description": "The werewolf speaks about setting aside differences; if successful, all listeners gain a +1 modifier to Resolve + Composure rolls to resist Death Rage for the scene."
      },
      {
        "id": "true_leader",
        "level": 3,
        "name": "True Leader",
        "cost": "1 Essence",
        "dice": "Manipulation + Expression + Glory",
        "action": "Instant",
        "description": "The werewolf leads allies into an obviously dangerous situation; for each success, a point of Willpower is awarded to all allies within 100 feet."
      },
      {
        "id": "spirit_skin",
        "level": 4,
        "name": "Spirit Skin",
        "cost": "None",
        "dice": "No roll required",
        "action": "Instant",
        "description": "The werewolf exudes a perceptible cloak of authority; the character's dots in his highest Renown are gained as a modifier to Social rolls to impress, persuade, inspire, or intimidate for the scene."
      },
      {
        "id": "victors_song",
        "level": 5,
        "name": "Victor's Song",
        "cost": "1 Essence",
        "dice": "Presence + Expression + Honor",
        "action": "Instant",
        "description": "The werewolf howls or sings to extoll his comrades to valor and courage; each success grants one Essence to all allied werewolves within earshot, and a one-die bonus is added to all allies' dice pools."
      }
    ]
  },
  "knowledge": {
    "id": "knowledge",
    "name": "Knowledge",
    "gifts": [
      {
        "id": "know_name",
        "level": 1,
        "name": "Know Name",
        "cost": "None",
        "dice": "Intelligence + Investigation + Cunning versus subject's Resolve + Primal Urge",
        "action": "Instant or contested; resistance is reflexive",
        "description": "With a glance, the werewolf can learn the name of someone she sees in person — always the name that person would answer to and consider his own."
      },
      {
        "id": "travelers_blessing",
        "level": 2,
        "name": "Traveler's Blessing",
        "cost": "1 Willpower per scene",
        "dice": "Wits + Streetwise + Wisdom",
        "action": "Reflexive",
        "description": "The local language settles into the werewolf's mouth and knowledge of local customs wraps around her mind, granting fluency and a +1 modifier to Social rolls to influence locals."
      },
      {
        "id": "sagacity",
        "level": 3,
        "name": "Sagacity",
        "cost": "1 Essence",
        "dice": "Wits + Occult + Purity",
        "action": "Instant",
        "description": "The werewolf becomes an instant expert in a Skill of her choice, temporarily gaining dots in that Skill equal to successes rolled, lasting one minute per success."
      },
      {
        "id": "know_the_path",
        "level": 4,
        "name": "Know the Path",
        "cost": "1 Essence",
        "dice": "Wits + Survival + Glory versus subject's Resolve + Primal Urge",
        "action": "Instant or contested; resistance is reflexive",
        "description": "The werewolf visualizes the closest and most efficient route to wherever she wants to go, stored as precise directions in her head for the duration of the scene."
      },
      {
        "id": "communion_with_the_land",
        "level": 5,
        "name": "Communion with the Land",
        "cost": "1 Essence",
        "dice": "Intelligence + Streetwise + Cunning",
        "action": "Instant",
        "description": "The werewolf opens her mind to her environment, gaining full knowledge of surroundings including entrances, exits, number of creatures present, and terrain features, with a +2 bonus to Defense and Initiative for the scene."
      }
    ]
  },
  "mother_luna": {
    "id": "mother_luna",
    "name": "Mother Luna",
    "gifts": [
      {
        "id": "partial_change",
        "level": 1,
        "name": "Partial Change",
        "cost": "None (or 1 Essence)",
        "dice": "Stamina + Survival + Primal Urge",
        "action": "Instant or reflexive",
        "description": "The werewolf transforms only the parts of himself he needs — such as his nose for tracking by scent or his eyes for sharper color vision — without undergoing a full shapechange."
      },
      {
        "id": "anybeast",
        "level": 2,
        "name": "Anybeast",
        "cost": "1 Essence",
        "dice": "No roll required",
        "action": "Instant",
        "description": "The werewolf camouflages himself in the skin of another carnivorous beast, allowing his Dalu, Gauru, Urshul, and Urhan forms to resemble other carnivores of similar size and build."
      },
      {
        "id": "silver_jaws",
        "level": 3,
        "name": "Silver Jaws",
        "cost": "1 Essence",
        "dice": "No roll required",
        "action": "Instant",
        "description": "The werewolf's teeth and claws transform into silver weaponry, inflicting aggravated damage rather than lethal against werewolves; using this Gift against other werewolves is a sin against Harmony."
      },
      {
        "id": "skin_stealing",
        "level": 4,
        "name": "Skin-Stealing",
        "cost": "1 Essence",
        "dice": "No roll required to activate",
        "action": "Instant",
        "description": "The werewolf sheathes himself in the skin of almost any human whose blood he has tasted, creating a near-perfect disguise that grants four bonus successes to disguise rolls."
      },
      {
        "id": "primal_form",
        "level": 5,
        "name": "Primal Form",
        "cost": "1 Essence",
        "dice": "Stamina + Survival + Primal Urge",
        "action": "Instant",
        "description": "The werewolf transforms into a terrifying prehistoric Primal Form standing six to eight feet tall at the shoulder, with greatly enhanced Attributes, lethal damage regeneration each turn, and Lunacy as if in Gauru."
      }
    ]
  },
  "nature": {
    "id": "nature",
    "name": "Nature",
    "gifts": [
      {
        "id": "speak_with_beasts",
        "level": 1,
        "name": "Speak with Beasts",
        "cost": "None",
        "dice": "Manipulation + Animal Ken + Purity",
        "action": "Reflexive",
        "description": "The werewolf communicates with any animal using voice and body language, though the animal has no obligation to listen or cooperate; the effect lasts one minute."
      },
      {
        "id": "plant_growth",
        "level": 2,
        "name": "Plant Growth",
        "cost": "1 Willpower",
        "dice": "Wits + Survival + Honor",
        "action": "Instant",
        "description": "Each success increases a plant or group of plants by one cubic yard per minute, shaping vegetation into any desired form permanently."
      },
      {
        "id": "forest_communion",
        "level": 3,
        "name": "Forest Communion",
        "cost": "1 Essence",
        "dice": "Manipulation + Survival + Cunning",
        "action": "Instant",
        "description": "Entering a trance, the werewolf senses life within 500 yards — presence of intruders, potential fires, and fleeting glimpses through the senses of nearby animals."
      },
      {
        "id": "beast_ride",
        "level": 4,
        "name": "Beast Ride",
        "cost": "1 Essence",
        "dice": "Wits + Animal Ken + Wisdom – animal's Resolve",
        "action": "Instant",
        "description": "The werewolf enters the mind of a mammal or bird, sensing what it does and exerting influence over where it goes; the ride lasts one hour per success rolled."
      },
      {
        "id": "natures_vengeance",
        "level": 5,
        "name": "Nature's Vengeance",
        "cost": "1 Essence",
        "dice": "Intelligence + Survival + Glory",
        "action": "Instant",
        "description": "The werewolf animates roughly 25 square yards of vegetation per success, causing branches, vines, and grasses to smash, entangle, and attack those marked as enemies."
      }
    ]
  },
  "new_moon": {
    "id": "new_moon",
    "name": "New Moon",
    "gifts": [
      {
        "id": "sense_weakness",
        "level": 1,
        "name": "Sense Weakness",
        "cost": "None",
        "dice": "Intelligence + Empathy + Wisdom",
        "action": "Instant",
        "description": "By observing a target for one turn, the werewolf learns one of three possible weaknesses: the target's Vice, any derangements the target suffers, or physical Flaws the character possesses."
      },
      {
        "id": "slip_away",
        "level": 2,
        "name": "Slip Away",
        "cost": "1 Willpower",
        "dice": "No roll is required",
        "action": "Reflexive",
        "description": "The Irraka automatically escapes any mundane physical bond — handcuffs, rope, or straitjacket — and succeeds automatically on any escape attempt from a grapple."
      },
      {
        "id": "distractions",
        "level": 3,
        "name": "Distractions",
        "cost": "1 Essence",
        "dice": "Manipulation + Subterfuge + Glory versus subject's Resolve + Primal Urge",
        "action": "Instant",
        "description": "The werewolf spits whispered yips and hisses that cause half-perceived visions, imposing a –2 penalty to all rolls for one chosen target each turn the Irraka maintains the effect."
      },
      {
        "id": "blend_in",
        "level": 4,
        "name": "Blend In",
        "cost": "1 Essence",
        "dice": "Wits + Subterfuge + Cunning versus the highest Wits among observers",
        "action": "Instant and contested; resistance is reflexive",
        "description": "The Irraka appears to belong in whatever environment he enters, becoming unnoticeable even to cameras and security systems for the duration of the scene."
      },
      {
        "id": "ghost_step",
        "level": 5,
        "name": "Ghost Step",
        "cost": "1 Essence",
        "dice": "Wits + Survival + Purity",
        "action": "Instant",
        "description": "The Irraka becomes insubstantial and ghostly — immune to physical attacks, scentless, and nearly imperceptible by sight — for a number of turns equal to his Harmony score."
      }
    ]
  },
  "rage": {
    "id": "rage",
    "name": "Rage",
    "gifts": [
      {
        "id": "mask_of_rage",
        "level": 1,
        "name": "Mask of Rage",
        "cost": "1 Essence",
        "dice": "No roll is required",
        "action": "Instant",
        "description": "The werewolf exposes onlookers to Lunacy as if in Gauru form regardless of his actual form; the effect lasts as long as he remains in the form in which he activated it."
      },
      {
        "id": "home_rage",
        "level": 2,
        "name": "Home Rage",
        "cost": "1 Essence",
        "dice": "Stamina + Survival + Purity",
        "action": "Reflexive",
        "description": "Each success allows the werewolf to sacrifice one Gauru turn for a temporary dot of Strength or Dexterity, lasting while he remains in Gauru form."
      },
      {
        "id": "leach_rage",
        "level": 3,
        "name": "Leach Rage",
        "cost": "1 Essence",
        "dice": "Presence + Empathy + Cunning – subject's Composure",
        "action": "Instant",
        "description": "The werewolf literally steals Gauru turns from a raging victim; for every success, the victim loses one turn in Gauru and the Gift user gains that turn."
      },
      {
        "id": "rekindled_rage",
        "level": 4,
        "name": "Rekindled Rage",
        "cost": "1 Willpower",
        "dice": "Stamina + Expression + Glory",
        "action": "Instant",
        "description": "The werewolf rekindles his Rage to enter Gauru form a second time in a scene, remaining in war form for a number of turns equal to Stamina + Primal Urge – 2 on success."
      },
      {
        "id": "soured_rage",
        "level": 5,
        "name": "Soured Rage",
        "cost": "1 Essence",
        "dice": "Manipulation + Intimidation + Purity versus Composure + Primal Urge",
        "action": "Contested; resistance is reflexive",
        "description": "A First Tongue curse poisons the victim's controlled Rage into a self-preservation instinct, causing the victim to flee in a mindless Death Rage for the rest of the scene."
      }
    ]
  },
  "shaping": {
    "id": "shaping",
    "name": "Shaping",
    "gifts": [
      {
        "id": "straighten",
        "level": 1,
        "name": "Straighten",
        "cost": "1 Essence",
        "dice": "No roll is required",
        "action": "Instant",
        "description": "The werewolf straightens kinks, warps, and imperfections in a physical object up to one square yard per turn, restoring it to original shape without repairing actual structural damage."
      },
      {
        "id": "ruin",
        "level": 2,
        "name": "Ruin",
        "cost": "1 Essence",
        "dice": "Wits + Crafts + Cunning",
        "action": "Instant",
        "description": "With a harsh bark, the werewolf causes an object up to one square yard in area to warp, twist, and crumple into a useless, gnarled mass."
      },
      {
        "id": "sculpt",
        "level": 3,
        "name": "Sculpt",
        "cost": "1 Essence per half an hour of work",
        "dice": "Intelligence + Crafts + Wisdom",
        "action": "Instant",
        "description": "The werewolf shapes up to one cubic yard of a non-living substance as if it were clay while maintaining physical contact, working and reshaping it for half an hour per Essence spent."
      },
      {
        "id": "shatter",
        "level": 4,
        "name": "Shatter",
        "cost": "1 Willpower",
        "dice": "Presence + Expression + Glory",
        "action": "Instant",
        "description": "The werewolf breaks down an object by touching it; each success removes one point of Structure, potentially crumbling it to dust or fracturing it like desert hardpan."
      },
      {
        "id": "condense_or_expand",
        "level": 5,
        "name": "Condense or Expand",
        "cost": "1 Willpower",
        "dice": "Intelligence + Crafts + Purity",
        "action": "Instant",
        "description": "The werewolf shrinks or enlarges an object while maintaining its mass, reducing Size by one while increasing Durability by two (or vice versa); the change is permanent."
      }
    ]
  },
  "stealth": {
    "id": "stealth",
    "name": "Stealth",
    "gifts": [
      {
        "id": "feet_of_mist",
        "level": 1,
        "name": "Feet of Mist",
        "cost": "1 Essence",
        "dice": "This power requires no roll",
        "action": "Reflexive",
        "description": "All attempts to track the werewolf by scent automatically suffer a –1 penalty; spending a Willpower point intensifies this to –3, though the werewolf may suppress the effect voluntarily."
      },
      {
        "id": "blending",
        "level": 2,
        "name": "Blending",
        "cost": "None",
        "dice": "Wits + Stealth + Cunning versus Wits + Composure",
        "action": "Instant or contested",
        "description": "The werewolf hides in plain sight by remaining perfectly still, becoming indistinguishable from a landscape feature; even the slightest movement ends the effect."
      },
      {
        "id": "running_shadow",
        "level": 3,
        "name": "Running Shadow",
        "cost": "1 Essence",
        "dice": "This power requires no roll",
        "action": "Reflexive",
        "description": "For the scene, mundane Stealth becomes reflexive — the werewolf can move at full speed as silently as on tiptoe, and observers suffer a –3 penalty on contested rolls to notice her."
      },
      {
        "id": "shadow_flesh",
        "level": 4,
        "name": "Shadow Flesh",
        "cost": "1 Essence",
        "dice": "Wits + Stealth + Cunning",
        "action": "Instant",
        "description": "The werewolf's body transforms into a living two-dimensional shadow, gaining +3 to Stealth and Defense and the ability to slip through small openings and under doors."
      },
      {
        "id": "vanish",
        "level": 5,
        "name": "Vanish",
        "cost": "2 Essence",
        "dice": "Wits + Stealth + Purity",
        "action": "Instant",
        "description": "The werewolf fades from all visual detection — cameras, heat sensors, and normal sight — for the scene, though the Gift offers no protection against non-visual senses."
      }
    ]
  },
  "strength": {
    "id": "strength",
    "name": "Strength",
    "gifts": [
      {
        "id": "crushing_blow",
        "level": 1,
        "name": "Crushing Blow",
        "cost": "1 Willpower",
        "dice": "No roll is necessary",
        "action": "Reflexive",
        "description": "For the duration of the scene, any bashing damage the werewolf inflicts with bare hands or a blunt instrument is converted to lethal damage."
      },
      {
        "id": "mighty_bound",
        "level": 2,
        "name": "Mighty Bound",
        "cost": "None",
        "dice": "None",
        "action": "None",
        "description": "The werewolf permanently gains six extra dice on all jumping rolls; the Gift's effects are always active once learned and require no activation."
      },
      {
        "id": "iron_rending",
        "level": 3,
        "name": "Iron-Rending",
        "cost": "1 Essence",
        "dice": "Strength + Crafts + Glory",
        "action": "Reflexive",
        "description": "The werewolf's claws can tear apart steel and stone; each success lets him ignore that many points of an object's Durability or a target's Armor for one turn per success rolled."
      },
      {
        "id": "legendary_arm",
        "level": 4,
        "name": "Legendary Arm",
        "cost": "1 Essence",
        "dice": "This power requires no roll",
        "action": "Reflexive",
        "description": "The werewolf can hurl any object while disregarding its Size, greatly extending its throwing range to Strength + Dexterity + Athletics yards for non-aerodynamic objects."
      },
      {
        "id": "savage_might",
        "level": 5,
        "name": "Savage Might",
        "cost": "1 Essence per three Strength gained",
        "dice": "This power requires no roll",
        "action": "Reflexive",
        "description": "Each Essence spent increases the werewolf's Strength by three dots for one turn, even beyond Primal Urge maximums, enabling feats of impossible physical power."
      }
    ]
  },
  "technology": {
    "id": "technology",
    "name": "Technology",
    "gifts": [
      {
        "id": "left_handed_spanner",
        "level": 1,
        "name": "Left-Handed Spanner",
        "cost": "1 Willpower",
        "dice": "Wits + Crafts + Purity",
        "action": "Instant",
        "description": "The werewolf channels spirit energy into a touched technological object, causing it to malfunction for a number of turns equal to successes rolled."
      },
      {
        "id": "nightfall",
        "level": 2,
        "name": "Nightfall",
        "cost": "1 Willpower",
        "dice": "Wits + Larceny + Cunning",
        "action": "Instant",
        "description": "The werewolf extinguishes all electric lighting in a targeted area of about 2,000 square feet per success, preventing those lights from functioning for the scene."
      },
      {
        "id": "iron_treachery",
        "level": 3,
        "name": "Iron Treachery",
        "cost": "1 Essence",
        "dice": "Wits + Crafts + Glory – Resolve",
        "action": "Instant",
        "description": "With a gesture and snarl, the werewolf awakens the spirit of a machine and drives it into angry independence — a pistol jerks, a steering wheel twists, a computer rebels."
      },
      {
        "id": "maschingeist",
        "level": 4,
        "name": "Maschingeist",
        "cost": "1 Essence",
        "dice": "Wits + Computer + Wisdom",
        "action": "Instant or extended (10 to 20 successes required; each roll represents a minute's time)",
        "description": "The werewolf merges his being with a machine's spirit, experiencing what it senses and accessing any knowledge or information it possesses for a number of turns equal to his Harmony."
      },
      {
        "id": "create_technology",
        "level": 5,
        "name": "Create Technology",
        "cost": "1 Essence + 1 Willpower",
        "dice": "Intelligence + Crafts + Cunning",
        "action": "Extended (5 to 50 successes required; one turn passes per roll)",
        "description": "Given rough materials, the werewolf rapidly creates sophisticated technological devices from almost nothing, accumulating 5 to 50 successes depending on the item's complexity."
      }
    ]
  },
  "warding": {
    "id": "warding",
    "name": "Warding",
    "gifts": [
      {
        "id": "ward_versus_predators",
        "level": 1,
        "name": "Ward Versus Predators",
        "cost": "None",
        "dice": "Presence + Intimidation + Honor",
        "action": "Extended (5 successes per square mile required; one hour per roll)",
        "description": "The werewolf marks territory up to one square mile per Primal Urge dot; all predatory animals instinctively recognize it as claimed land and avoid it for one lunar cycle."
      },
      {
        "id": "ward_versus_humans",
        "level": 2,
        "name": "Ward Versus Humans",
        "cost": "1 Willpower",
        "dice": "Presence + Intimidation + Wisdom",
        "action": "Extended (5 successes per square mile required; one hour per roll)",
        "description": "The werewolf wards territory against humans, filling those who enter with unparalleled dread and a powerful compulsion to flee; the ward persists for one lunar cycle."
      },
      {
        "id": "technology_ward",
        "level": 3,
        "name": "Technology Ward",
        "cost": "1 Essence",
        "dice": "Presence + Crafts + Cunning",
        "action": "Instant",
        "description": "The werewolf's howl creates a spiritual barrier rendering all electronic items and complex mechanical devices useless within five feet per success rolled for the scene."
      },
      {
        "id": "shadow_ward",
        "level": 4,
        "name": "Shadow Ward",
        "cost": "1 Essence",
        "dice": "Presence + Occult + Glory",
        "action": "Extended (30 successes; one hour per roll)",
        "description": "The werewolf outlines territory with ritual designs, strengthening the Gauntlet in the warded area by one per success for one lunar cycle; the caster can reverse the effect by spending one Essence."
      },
      {
        "id": "ward_of_spirit_slumber",
        "level": 5,
        "name": "Ward of Spirit Slumber",
        "cost": "1 Essence",
        "dice": "Manipulation + Occult + Purity versus Resistance",
        "action": "Instant, can be contested",
        "description": "The werewolf sings Luna's lullaby through the Gauntlet, lulling spirits in the warded area into a deep enchanted slumber for one turn per success that can last for days."
      }
    ]
  },
  "weather": {
    "id": "weather",
    "name": "Weather",
    "gifts": [
      {
        "id": "call_the_breeze",
        "level": 1,
        "name": "Call the Breeze",
        "cost": "None",
        "dice": "This power requires no roll",
        "action": "Instant",
        "description": "The werewolf summons a brisk wind of about 25 miles per hour and directs it at will, causing a –1 penalty to perception rolls in the area; the breeze lasts one turn per Primal Urge dot."
      },
      {
        "id": "silent_fog",
        "level": 2,
        "name": "Silent Fog",
        "cost": "1 Essence",
        "dice": "Manipulation + Survival + Cunning",
        "action": "Instant",
        "description": "The werewolf summons a dense fog bank covering Primal Urge × 20 square yards that can be directed at (Primal Urge × 10) yards per turn, imposing a –2 penalty to perception checks."
      },
      {
        "id": "deluge",
        "level": 3,
        "name": "Deluge",
        "cost": "1 Essence",
        "dice": "Manipulation + Survival + Honor",
        "action": "Extended (20 successes; one turn passes per roll)",
        "description": "The werewolf summons a torrential downpour across one square mile per success, capable of flooding low-lying areas, ruining crops, or erasing evidence of a pack's passage."
      },
      {
        "id": "killing_frost",
        "level": 4,
        "name": "Killing Frost",
        "cost": "1 Essence",
        "dice": "Manipulation + Survival + Purity",
        "action": "Instant",
        "description": "Temperature plunges below freezing within 10 yards per Primal Urge dot, inflicting 2 bashing damage on living creatures and imposing –2 to Strength and Dexterity for the cold's duration."
      },
      {
        "id": "thunderbolt",
        "level": 5,
        "name": "Thunderbolt",
        "cost": "1 Essence",
        "dice": "Intelligence + Survival + Glory – Defense",
        "action": "Instant",
        "description": "The werewolf commands a thunderbird to strike a chosen foe with lightning, dealing a base of 5 lethal damage plus extra successes; the target must be outdoors or near a window."
      }
    ]
  }
}
